[
    {
      "title": "برنامه آزمون دی",
      "summary": "زمان‌بندی آزمون‌های آنلاین و حضوری برای پایه‌های هفتم تا نهم منتشر شد.",
      "date": "1404/10/06"
    },
    {
      "title": "جزوه‌های جدید علوم",
      "summary": "نسخه‌های به‌روزرسانی‌شده‌ی جزوه‌های فصل‌های 3 و 4 اضافه شد.",
      "date": "1404/10/05"
    },
    {
      "title": "ویدیوهای آموزشی ریاضی",
      "summary": "سری جدید ویدیوهای حل تمرین با رویکرد مفهومی در دسترس است.",
      "date": "1404/10/04"
    }
  ]